Flask_ADFS-0.1.19.dist-info/DESCRIPTION.rst
Flask_ADFS-0.1.19.dist-info/METADATA
Flask_ADFS-0.1.19.dist-info/RECORD
Flask_ADFS-0.1.19.dist-info/WHEEL
Flask_ADFS-0.1.19.dist-info/metadata.json
Flask_ADFS-0.1.19.dist-info/top_level.txt
flask_adfs/__about__.py
flask_adfs/__init__.py
flask_adfs/adfs.py
flask_adfs/decorators.py
flask_adfs/initialise.py
flask_adfs/model.py
