Metadata-Version: 2.0
Name: Flask-ADFS
Version: 0.1.19
Summary: User session management for Flask
Home-page: https://github.com/johnpickerill/flask-login
Author: John Pickerill
Author-email: john.pickerill@landregistry.gov.uk
License: MIT
Platform: any
Classifier: Development Status :: 4 - Beta
Classifier: Environment :: Web Environment
Classifier: Intended Audience :: Developers
Classifier: License :: OSI Approved :: BSD License
Classifier: Operating System :: OS Independent
Classifier: Programming Language :: Python
Classifier: Programming Language :: Python :: 3.3
Classifier: Programming Language :: Python :: 3.4
Classifier: Programming Language :: Python :: 3.5
Classifier: Programming Language :: Python :: Implementation :: PyPy
Classifier: Topic :: System :: Systems Administration :: Authentication/Directory :: LDAP
Classifier: Topic :: Software Development :: Libraries :: Python Modules
Requires-Dist: Flask (>=0.12)
Requires-Dist: Flask-Login (>=0.3.2)
Requires-Dist: python-jose (==1.3.2)
Requires-Dist: xmltodict (==0.11.0)
